lytool/QRcode.py
lytool/__init__.py
lytool/analysis_html_by_xpath_re.py
lytool/chaojiying.py
lytool/createFile.py
lytool/df_to_list_dict.py
lytool/down_img_url.txt
lytool/fileOperation.py
lytool/get_selenium_cookies_dict.py
lytool/headers.py
lytool/imageRecognition.py
lytool/imageToWord.py
lytool/imageTool.py
lytool/init_self_headers.py
lytool/json_nested.py
lytool/mobilePhon.py
lytool/myClient.py
lytool/myEcharts.py
lytool/myExecjs.py
lytool/myJieBa.py
lytool/myLog.py
lytool/myMD5.py
lytool/myMakDir.py
lytool/myPickle.py
lytool/myPlot.py
lytool/myQRCode.png
lytool/myRandomUserAgent.py
lytool/myRequests.py
lytool/myServer.py
lytool/mySpider.py
lytool/mySql.py
lytool/myTTS.py
lytool/myTime.py
lytool/myTkinter.py
lytool/myToken.py
lytool/my_qr_code.py
lytool/objectStringMethod.py
lytool/objectSvgMethod.py
lytool/operating_mongodb.py
lytool/operating_mysql.py
lytool/operating_redis.py
lytool/operating_sqlite.py
lytool/processed_image.png
lytool/regularExpression.py
lytool/rgb_ras_stack.py
lytool/runJs.py
lytool/runNum.py
lytool/rwfile.py
lytool/sendEmail.py
lytool/speechRecognition.py
lytool/timer.py
lytool/xiciCrawler.py
lytool/yundama.py
lytool/快速将chrom复制的headers转变成字典.py
lytool/重命名.py
lytool/.idea/.gitignore
lytool/.idea/lytool.iml
lytool/.idea/misc.xml
lytool/.idea/modules.xml
lytool/.idea/workspace.xml
lytool/.idea/inspectionProfiles/Project_Default.xml
lytool/.idea/inspectionProfiles/profiles_settings.xml
lytool/AdslProxy-master/.gitignore
lytool/AdslProxy-master/LICENSE
lytool/AdslProxy-master/README.md
lytool/AdslProxy-master/__init__.py
lytool/AdslProxy-master/api.py
lytool/AdslProxy-master/run.py
lytool/AdslProxy-master/setup.py
lytool/AdslProxy-master/adslproxy/__init__.py
lytool/AdslProxy-master/adslproxy/api.py
lytool/AdslProxy-master/adslproxy/config.py
lytool/AdslProxy-master/adslproxy/db.py
lytool/AdslProxy-master/adslproxy/sender.py
lytool/AdslProxy-master/test/__init__.py
lytool/AdslProxy-master/test/proxy.py
lytool/multimedia/compressedVideo.py
lytool-0.0.35.dist-info/METADATA
lytool-0.0.35.dist-info/WHEEL
lytool-0.0.35.dist-info/licenses/LICENSE
lytool-0.0.35.dist-info/RECORD
