Metadata-Version: 2.4
Name: lytool
Version: 0.0.35
Summary: CommonTools
Project-URL: Homepage, https://github.com/18086829907/lytool
Author-email: longliangyu112233 <2476673550@qq.com>
License: Copyright (c) 2018 The Python Packaging Authority
License-File: LICENSE
Classifier: License :: OSI Approved :: MIT License
Classifier: Operating System :: OS Independent
Classifier: Programming Language :: Python :: 3
Requires-Python: >=3.7
